nimlite/__init__.py
nimlite/libnimlite.pyd
nimlite/libnimlite.pyi
nimlite/libnimlite.so
tablite/__init__.py
tablite/base.py
tablite/config.py
tablite/core.py
tablite/datasets.py
tablite/datatypes.py
tablite/diff.py
tablite/export_utils.py
tablite/file_reader_utils.py
tablite/groupby_utils.py
tablite/import_utils.py
tablite/imputation.py
tablite/joins.py
tablite/lookup.py
tablite/match.py
tablite/merge.py
tablite/mp_utils.py
tablite/nimlite.py
tablite/pivots.py
tablite/redux.py
tablite/reindex.py
tablite/sort_utils.py
tablite/sortation.py
tablite/tools.py
tablite/utils.py
tablite/version.py
tablite-2023.11.6.data/data/LICENSE
tablite-2023.11.6.data/data/README.md
tablite-2023.11.6.data/data/requirements.txt
tablite-2023.11.6.dist-info/LICENSE
tablite-2023.11.6.dist-info/METADATA
tablite-2023.11.6.dist-info/WHEEL
tablite-2023.11.6.dist-info/top_level.txt
tablite-2023.11.6.dist-info/RECORD
