Metadata-Version: 2.1
Name: tablite
Version: 2023.11.6
Summary: multiprocessing enabled out-of-memory data analysis library for tabular data.
Home-page: https://github.com/root-11/tablite
Author: https://github.com/root-11
License: MIT
Keywords: all,any,average,column,columns,count,csv,data imputation,date range,dict,excel,filter,first,from,from_pandas,groupby,guess,imputation,in-memory,index,indexing,inner join,is sorted,json,last,left join,list,list on disk,log,max,median,min,mode,numpy,ods,out-of-memory,outer join,pandas,pivot,pivot table,product,read csv,remove duplicates,replace,replace missing values,rows,show,sort,standard deviation,stored list,sum,table,tables,tablite,to,to_pandas,tools,transpose,txt,unique,use disk,xl
Platform: any
Classifier: Development Status :: 5 - Production/Stable
Classifier: Intended Audience :: Science/Research
Classifier: Natural Language :: English
Classifier: License :: OSI Approved :: MIT License
Classifier: Programming Language :: Python :: 3.8
Classifier: Programming Language :: Python :: 3.9
Classifier: Programming Language :: Python :: 3.10
Classifier: Programming Language :: Python :: 3.11
Classifier: Programming Language :: Python :: 3.12
Requires-Python: >=3.8
License-File: LICENSE
Requires-Dist: tqdm >=4.63.0
Requires-Dist: numpy ==1.24.3
Requires-Dist: psutil >=5.9.5
Requires-Dist: chardet ==5.1.0
Requires-Dist: pyexcel ==0.7.0
Requires-Dist: pyexcel-odsr ==0.6.0
Requires-Dist: pyexcel-ods ==0.6.0
Requires-Dist: pyexcel-xlsx ==0.6.0
Requires-Dist: pyexcel-xls ==0.7.0
Requires-Dist: pandas >=2.2.1
Requires-Dist: pyuca >=1.2
Requires-Dist: mplite >=1.3.0
Requires-Dist: PyYAML ==6.0
Requires-Dist: openpyxl ==3.0.10
Requires-Dist: h5py >=3.6.0
Requires-Dist: nimporter
Requires-Dist: python-dotenv
